linuxnet/__init__.py
linuxnet/iptables/__init__.py
linuxnet/iptables/chain.py
linuxnet/iptables/deps.py
linuxnet/iptables/exceptions.py
linuxnet/iptables/extension.py
linuxnet/iptables/metadata.py
linuxnet/iptables/parsing.py
linuxnet/iptables/rule.py
linuxnet/iptables/table.py
linuxnet/iptables/matches/__init__.py
linuxnet/iptables/matches/addrtypematch.py
linuxnet/iptables/matches/commentmatch.py
linuxnet/iptables/matches/connbytesmatch.py
linuxnet/iptables/matches/connmarkmatch.py
linuxnet/iptables/matches/conntrackmatch.py
linuxnet/iptables/matches/icmpmatch.py
linuxnet/iptables/matches/lengthmatch.py
linuxnet/iptables/matches/limitmatch.py
linuxnet/iptables/matches/macmatch.py
linuxnet/iptables/matches/markmatch.py
linuxnet/iptables/matches/match.py
linuxnet/iptables/matches/multiportmatch.py
linuxnet/iptables/matches/ownermatch.py
linuxnet/iptables/matches/packetmatch.py
linuxnet/iptables/matches/packettypematch.py
linuxnet/iptables/matches/recentmatch.py
linuxnet/iptables/matches/setmatch.py
linuxnet/iptables/matches/statematch.py
linuxnet/iptables/matches/statisticmatch.py
linuxnet/iptables/matches/tcpmatch.py
linuxnet/iptables/matches/tcpmssmatch.py
linuxnet/iptables/matches/ttlmatch.py
linuxnet/iptables/matches/udpmatch.py
linuxnet/iptables/matches/util.py
linuxnet/iptables/targets/__init__.py
linuxnet/iptables/targets/connmarktarget.py
linuxnet/iptables/targets/logtarget.py
linuxnet/iptables/targets/marktarget.py
linuxnet/iptables/targets/masqueradetarget.py
linuxnet/iptables/targets/nattarget.py
linuxnet/iptables/targets/nflogtarget.py
linuxnet/iptables/targets/notracktarget.py
linuxnet/iptables/targets/rejecttarget.py
linuxnet/iptables/targets/settarget.py
linuxnet/iptables/targets/target.py
linuxnet/iptables/targets/tracetarget.py
linuxnet/iptables/targets/ttltarget.py
linuxnet_iptables-7.6.5.dist-info/licenses/LICENSE
linuxnet_iptables-7.6.5.dist-info/METADATA
linuxnet_iptables-7.6.5.dist-info/WHEEL
linuxnet_iptables-7.6.5.dist-info/top_level.txt
linuxnet_iptables-7.6.5.dist-info/RECORD
