Metadata-Version: 2.4
Name: linuxnet-iptables
Version: 7.6.5
Summary: programmatic access to Linux iptables
Home-page: https://gitlab.com/panos-tools/linuxnet-iptables
Author: Panagiotis (Panos) Tsirigotis
Author-email: ptsirigotis01@gmail.com
License: AGPLv3
Project-URL: Source, https://gitlab.com/panos-tools/linuxnet-iptables
Project-URL: Documentation, https://linuxnet-iptables.readthedocs.io/en/latest/index.html
Classifier: Development Status :: 5 - Production/Stable
Classifier: Intended Audience :: Developers
Classifier: License :: OSI Approved :: GNU Affero General Public License v3
Classifier: Operating System :: POSIX :: Linux
Classifier: Programming Language :: Python :: 3 :: Only
Classifier: Topic :: Software Development :: Libraries
Classifier: Topic :: System :: Networking :: Firewalls
Requires-Python: >=3.6
License-File: LICENSE
Dynamic: author
Dynamic: author-email
Dynamic: classifier
Dynamic: description
Dynamic: description-content-type
Dynamic: home-page
Dynamic: license
Dynamic: license-file
Dynamic: project-url
Dynamic: requires-python
Dynamic: summary
